schedulebt/__init__.py
schedulebt-0.1.7.dist-info/METADATA
schedulebt-0.1.7.dist-info/WHEEL
schedulebt-0.1.7.dist-info/top_level.txt
schedulebt-0.1.7.dist-info/RECORD
