Metadata-Version: 2.1
Name: schedulebt
Version: 0.1.7
Summary: A simple tools to optimize work schedule and estimate finish duration distribution
Home-page: 
Author: 
Classifier: Programming Language :: Python :: 3
Classifier: License :: OSI Approved :: MIT License
Classifier: Operating System :: OS Independent
Requires-Python: >=3.6
Requires-Dist: cvxpy
Requires-Dist: pyscipopt
